{
  "accentColor": "{{appsmith.theme.colors.primaryColor}}",
  "borderRadius": "0px",
  "bottomRow": 36,
  "boxShadow": "none",
  "childStylesheet": {
    "button": {
      "borderRadius": "{{appsmith.theme.borderRadius.appBorderRadius}}",
      "boxShadow": "none",
      "buttonColor": "{{appsmith.theme.colors.primaryColor}}"
    },
    "iconButton": {
      "borderRadius": "{{appsmith.theme.borderRadius.appBorderRadius}}",
      "boxShadow": "none",
      "menuColor": "{{appsmith.theme.colors.primaryColor}}"
    },
    "menuButton": {
      "borderRadius": "{{appsmith.theme.borderRadius.appBorderRadius}}",
      "boxShadow": "none",
      "menuColor": "{{appsmith.theme.colors.primaryColor}}"
    }
  },
  "columnOrder": [
    "Id",
    "DishName"
  ],
  "columnSizeMap": {
    "DishName": 251,
    "Id": 256,
    "PreferenceType": 309,
    "TypeName": 438,
    "status": 75,
    "step": 223,
    "task": 377
  },
  "defaultPageSize": 0,
  "defaultSelectedRow": "0",
  "delimiter": ",",
  "derivedColumns": {},
  "displayName": "Table",
  "dynamicBindingPathList": [
    {
      "key": "tableData"
    },
    {
      "key": "primaryColumns.DishName.computedValue"
    },
    {
      "key": "primaryColumns.Id.computedValue"
    },
    {
      "key": "accentColor"
    }
  ],
  "dynamicPropertyPathList": [],
  "dynamicTriggerPathList": [],
  "hideCard": false,
  "horizontalAlignment": "LEFT",
  "iconSVG": "/static/media/icon.59df0390.svg",
  "isLoading": false,
  "isSortable": true,
  "isVisible": true,
  "isVisibleDownload": false,
  "isVisibleFilters": false,
  "isVisiblePagination": true,
  "isVisibleSearch": false,
  "key": "dc0eoioaus",
  "label": "Data",
  "labelTextSize": "0.875rem",
  "leftColumn": 1,
  "multiRowSelection": false,
  "parentColumnSpace": 16.1828125,
  "parentId": "0",
  "parentRowSpace": 10,
  "primaryColumns": {
    "DishName": {
      "borderRadius": "0px",
      "boxShadow": "none",
      "columnType": "text",
      "computedValue": "{{Table1.sanitizedTableData.map((currentRow) => ( currentRow.DishName))}}",
      "enableFilter": true,
      "enableSort": true,
      "horizontalAlignment": "LEFT",
      "id": "DishName",
      "index": 0,
      "isCellVisible": true,
      "isDerived": false,
      "isDisabled": false,
      "isVisible": true,
      "label": "DishName",
      "textSize": "0.875rem",
      "verticalAlignment": "CENTER",
      "width": 150
    },
    "Id": {
      "borderRadius": "0px",
      "boxShadow": "none",
      "columnType": "text",
      "computedValue": "{{Table1.sanitizedTableData.map((currentRow) => ( currentRow.Id))}}",
      "enableFilter": true,
      "enableSort": true,
      "horizontalAlignment": "LEFT",
      "id": "Id",
      "index": 0,
      "isCellVisible": true,
      "isDerived": false,
      "isDisabled": false,
      "isVisible": true,
      "label": "Id",
      "textSize": "0.875rem",
      "verticalAlignment": "CENTER",
      "width": 150
    }
  },
  "renderMode": "CANVAS",
  "rightColumn": 63,
  "searchKey": "",
  "tableData": "{{cart_items.data}}",
  "textSize": "0.875rem",
  "topRow": 5,
  "totalRecordsCount": 0,
  "type": "TABLE_WIDGET",
  "version": 3,
  "verticalAlignment": "CENTER",
  "widgetId": "mg5sahcdjt",
  "widgetName": "Table1"
}